README.md
setup.cfg
setup.py
pytriplet.egg-info/PKG-INFO
pytriplet.egg-info/SOURCES.txt
pytriplet.egg-info/dependency_links.txt
pytriplet.egg-info/requires.txt
pytriplet.egg-info/top_level.txt
ttt/__init__.py
ttt/args.py
ttt/evaluators.py
ttt/inputs.py
ttt/models.py
ttt/t2t_trainer.py
ttt/utils.py