Metadata-Version: 2.1
Name: pytriplet
Version: 0.0.3
Summary: Fine-tuning Transformers with TPUs or GPUs acceleration, written in Tensorflow2.0
Home-page: https://github.com/wangcongcong123/ttt
Author: Congcong Wang
Author-email: wangcongcongcc@gmail.com
License: MIT License
Download-URL: https://github.com/wangcongcong123/ttt/releases/download/v0.0.3/pytriplet.tar.gz
Keywords: Transformers,Tensorflow,TPUs acceleration
Platform: UNKNOWN
Classifier: Development Status :: 4 - Beta
Classifier: Intended Audience :: Science/Research
Classifier: License :: OSI Approved :: Apache Software License
Classifier: Programming Language :: Python :: 3.7
Classifier: Topic :: Scientific/Engineering :: Artificial Intelligence
